lsmetrics/__init__.py
lsmetrics/analysis/__init__.py
lsmetrics/analysis/latent_analyzer.py
lsmetrics/analysis/metrics.py
lsmetrics/analysis/visualization.py
lsmetrics/data/__init__.py
lsmetrics/data/atom_init.py
lsmetrics/data/dataloader.py
lsmetrics/data/edge_features.py
lsmetrics/data/node_features.py
lsmetrics/model/__init__.py
lsmetrics/model/csgann.py
lsmetrics/model/csgcnn.py
lsmetrics/model/csgcnn_vae.py
lsmetrics/model/flow.py
lsmetrics/model/flowgnn.py
lsmetrics/utils/checkpoint.py
lsmetrics/utils/file_io.py
lsmetrics-0.3.0.dist-info/LICENSE
lsmetrics-0.3.0.dist-info/METADATA
lsmetrics-0.3.0.dist-info/WHEEL
lsmetrics-0.3.0.dist-info/top_level.txt
lsmetrics-0.3.0.dist-info/RECORD
